simpleterraform/__init__.py
simpleterraform/cli.py
simpleterraform/main.py
simpleterraform/modules/__init__.py
simpleterraform/modules/generate_compute.py
simpleterraform/modules/generate_database.py
simpleterraform/modules/generate_ecs.py
simpleterraform/modules/generate_kubernetes.py
simpleterraform/modules/generate_monitoring.py
simpleterraform/modules/generate_networking.py
simpleterraform/modules/generate_security.py
simpleterraform/modules/generate_storage.py
simpleterraform-0.1.3.dist-info/licenses/LICENSE
simpleterraform-0.1.3.dist-info/METADATA
simpleterraform-0.1.3.dist-info/WHEEL
simpleterraform-0.1.3.dist-info/entry_points.txt
simpleterraform-0.1.3.dist-info/top_level.txt
simpleterraform-0.1.3.dist-info/RECORD
