Metadata-Version: 2.4
Name: simpleterraform
Version: 0.1.3
Summary: CLI tool to generate Terraform module folder structure — made with ❤️ by Sourav Kumar Singh
Author-email: Sourav Kumar Singh <1109souravkumar@example.com>
Requires-Python: >=3.8
License-File: LICENSE
Dynamic: license-file
